README.md
setup.py
qr_code_generator/__init__.py
qr_code_generator/__main__.py
qr_code_generator/helpers.py
qr_code_generator/wrapper.py
qr_code_generator/errors/__init__.py
qr_code_generator_api.egg-info/PKG-INFO
qr_code_generator_api.egg-info/SOURCES.txt
qr_code_generator_api.egg-info/dependency_links.txt
qr_code_generator_api.egg-info/entry_points.txt
qr_code_generator_api.egg-info/requires.txt
qr_code_generator_api.egg-info/top_level.txt