Metadata-Version: 2.1
Name: qr-code-generator-api
Version: 0.1.2
Summary: Python wrapper for qr-code-generator.com API
Home-page: https://github.com/jobveldhuis/python-qr-code-generator-api
Author: Job Veldhuis
Author-email: job@baukefrederik.me
License: UNKNOWN
Platform: UNKNOWN
Classifier: Programming Language :: Python :: 3
Classifier: Development Status :: 4 - Beta
Classifier: Intended Audience :: Developers
Classifier: Topic :: Software Development
Classifier: License :: OSI Approved :: MIT License
Classifier: Operating System :: OS Independent
Requires-Python: >=3.6
